{
  "ShopItemPool\u0000": "ArrayProperty\u0000",
  "TreasureItemPool\u0000": "ArrayProperty\u0000",
  "BossItemPool\u0000": "ArrayProperty\u0000",
  "WeaponPool\u0000": "ArrayProperty\u0000",
  "WeaponCheapPool\u0000": "ArrayProperty\u0000",
  "WeaponAffordablePool\u0000": "ArrayProperty\u0000",
  "WeaponExpensivePool\u0000": "ArrayProperty\u0000",
  "LibrarySecondaryPool\u0000": "ArrayProperty\u0000",
  "LibraryUltimatePool\u0000": "ArrayProperty\u0000",
  "ChoiceRoomItemsPoolHead\u0000": "ArrayProperty\u0000",
  "ChoiceRoomItemsPoolFoot\u0000": "ArrayProperty\u0000",
  "ChoiceRoomItemsPoolShield\u0000": "ArrayProperty\u0000",
  "ChoiceRoomItemsPoolArm\u0000": "ArrayProperty\u0000",
  "DevilStatuePool\u0000": "ArrayProperty\u0000",
  "AngelStatuePool\u0000": "ArrayProperty\u0000",
  "CursedChestPool\u0000": "ArrayProperty\u0000",
  "FutureProofingAPool\u0000": "ArrayProperty\u0000",
  "FutureProofingBPool\u0000": "ArrayProperty\u0000",
  "FloorGenerationSeeds\u0000": "IntProperty\u0000",
  "FloorModifierFloats\u0000": "FloatProperty\u0000",
  "FloorPlaySeeds\u0000": "IntProperty\u0000",
  "BPMDifficulty\u0000": "EnumProperty\u0000",
  "LibraryBeforeArmoury\u0000": "IntProperty\u0000",
  "MinibossChoice\u0000": "IntProperty\u0000",
  "ChoiceRoomChosen\u0000": "IntProperty\u0000",
  "BankRoomChosen\u0000": "IntProperty\u0000",
  "ChallengeRoomChosen\u0000": "IntProperty\u0000",
  "StairsRoomChosen\u0000": "IntProperty\u0000",
  "HeroRoomChosen\u0000": "IntProperty\u0000",
  "GamblingRoomChosen\u0000": "IntProperty\u0000",
  "RerollRoomChosen\u0000": "IntProperty\u0000",
  "PrestigeRoomChosen\u0000": "IntProperty\u0000",
  "BlackMarketRoomChosen\u0000": "IntProperty\u0000",
  "bChallenge\u0000": "BoolProperty\u0000",
  "ChallengeNumber\u0000": "IntProperty\u0000",
  "PortalRoomChosen\u0000": "IntProperty\u0000",
  "FloorIndex\u0000": "IntProperty\u0000",
  "SpecialChapterVisit\u0000": "EnumProperty\u0000"
}